pybscope/__init__.py
pybscope/cli.py
pybscope/example.py
pybscope-0.1.0.dist-info/LICENSE
pybscope-0.1.0.dist-info/METADATA
pybscope-0.1.0.dist-info/WHEEL
pybscope-0.1.0.dist-info/top_level.txt
pybscope-0.1.0.dist-info/RECORD
